[
  {
    "country": "AS",
    "geonameid": 5880828,
    "name": "Aua",
    "alternatenames": "Aua,`Ava Point",
    "subcountry": "Eastern District"
  },
  {
    "country": "AS",
    "geonameid": 5880891,
    "name": "Vaitogi",
    "alternatenames": "",
    "subcountry": "Western District"
  },
  {
    "country": "AS",
    "geonameid": 5880944,
    "name": "Vailoatai",
    "alternatenames": "Vailoa",
    "subcountry": "Western District"
  },
  {
    "country": "AS",
    "geonameid": 5881150,
    "name": "Taulaga",
    "alternatenames": "",
    "subcountry": "Swains Island"
  },
  {
    "country": "AS",
    "geonameid": 5881165,
    "name": "Ta`u",
    "alternatenames": "Opoun,TAV,Ta`u,Ta`ue Village,Ta`ü Village,Tau",
    "subcountry": "Manu'a"
  },
  {
    "country": "AS",
    "geonameid": 5881192,
    "name": "Tafuna",
    "alternatenames": "Tafuna,Тафуна",
    "subcountry": "Western District"
  },
  {
    "country": "AS",
    "geonameid": 5881224,
    "name": "Faleniu",
    "alternatenames": "",
    "subcountry": "Western District"
  },
  {
    "country": "AS",
    "geonameid": 5881241,
    "name": "Fagatogo",
    "alternatenames": "Fagatogo,Fanga Tonga,Фагатого",
    "subcountry": "Eastern District"
  },
  {
    "country": "AS",
    "geonameid": 5881254,
    "name": "Faleasao",
    "alternatenames": "Faleasao,Faleasau",
    "subcountry": "Manu'a"
  },
  {
    "country": "AS",
    "geonameid": 5881347,
    "name": "Leone",
    "alternatenames": "",
    "subcountry": "Western District"
  },
  {
    "country": "AS",
    "geonameid": 5881410,
    "name": "Malaeimi",
    "alternatenames": "",
    "subcountry": "Western District"
  },
  {
    "country": "AS",
    "geonameid": 5881442,
    "name": "Mapusagafou",
    "alternatenames": "",
    "subcountry": "Western District"
  },
  {
    "country": "AS",
    "geonameid": 5881544,
    "name": "Ofu",
    "alternatenames": "OFU",
    "subcountry": "Manu'a"
  },
  {
    "country": "AS",
    "geonameid": 5881576,
    "name": "Pago Pago",
    "alternatenames": "PPG,Paga-Paga,Pago Pago,Pago-Pago,PagoPago,Pagopago,Pagó Pagó,Panko Panko,Paqo Paqo,baghw baghw,pa guo pa guo,pa ko pa ko,pago pago,pagopago,pagw pagw,pako pako,pango pango,Πάγκο Πάγκο,Пага-Пага,Паго Паго,Паго-Паго,Пагопаго,Պագո Պագո,פאגו פאגו,باغو باغو,پاگو پاگو,पांगो पांगो,பாகோ பாகோ,ปาโกปาโก,პაგო-პაგო,パゴパゴ,帕果帕果,파고 파고,파고파고",
    "subcountry": "Eastern District"
  }
]
