[
  {
    "country": "BJ",
    "geonameid": 2390751,
    "name": "Zagnanado",
    "alternatenames": "Zangnanado",
    "subcountry": "Zou"
  },
  {
    "country": "BJ",
    "geonameid": 2391377,
    "name": "Tchaourou",
    "alternatenames": "Chauru,Tchaourou",
    "subcountry": "Borgou"
  },
  {
    "country": "BJ",
    "geonameid": 2391455,
    "name": "Tanguieta",
    "alternatenames": "Tangoueita,Tangueita,Tanguieta,Tanguiéta",
    "subcountry": "Atakora"
  },
  {
    "country": "BJ",
    "geonameid": 2391699,
    "name": "So-Ava",
    "alternatenames": "So,So Avo,So-Ava,So-Awa,Sô Avo,Sô-Ava",
    "subcountry": "Atlantique"
  },
  {
    "country": "BJ",
    "geonameid": 2391833,
    "name": "Semi",
    "alternatenames": "Sami,Seme,Semi,Sèmè",
    "subcountry": "Ouémé"
  },
  {
    "country": "BJ",
    "geonameid": 2391880,
    "name": "Se",
    "alternatenames": "",
    "subcountry": "Atlantique"
  },
  {
    "country": "BJ",
    "geonameid": 2391893,
    "name": "Save",
    "alternatenames": "SVF,Save,Savé",
    "subcountry": "Collines"
  },
  {
    "country": "BJ",
    "geonameid": 2391895,
    "name": "Savalou",
    "alternatenames": "Savalou,Savalu",
    "subcountry": "Collines"
  },
  {
    "country": "BJ",
    "geonameid": 2392009,
    "name": "Sakete",
    "alternatenames": "Sakete,Sakété",
    "subcountry": "Plateau"
  },
  {
    "country": "BJ",
    "geonameid": 2392087,
    "name": "Porto-Novo",
    "alternatenames": "Borto-Novo,Porta-Nova,Porto Neuvo,Porto Nobo,Porto Novas,Porto Novo,Porto-Novo,Portonovo,Portus Novus,Poto-Novo,Pòrto Neuvo,Pòto-Novo,Pôrto-Novo,bo duo nuo fu,bo tu nu bu,bwrtw nwfw,poleutonobo,porato-novo,porto-novho,porutonobo,pwrtw nwbw,pwrtw nwww,pxr to-no wo,xin gang,Πόρτο Νόβο,Πόρτο-Νόβο,Порта-Нова,Порто Ново,Порто-Ново,Պորտո Նովո,פארטא-נאווא,פורטו נובו,بورتو نوفو,پورتو نووو,پورٹو نووو,پۆرتۆ نۆڤۆ,पोर्तो-नोव्हो,ਪੋਰਤੋ-ਨੋਵੋ,ปอร์โต-โนโว,པོར་ཊོ་-ནོ་བོ།,პორტო-ნოვო,ፖርቶ ኖቮ,ポルトノボ,新港,波圖奴埠,波多诺伏,포르토노보",
    "subcountry": "Ouémé"
  },
  {
    "country": "BJ",
    "geonameid": 2392108,
    "name": "Pobe",
    "alternatenames": "Ipobe,Pobe,Pobé",
    "subcountry": "Plateau"
  },
  {
    "country": "BJ",
    "geonameid": 2392204,
    "name": "Parakou",
    "alternatenames": "PKO,Parakou,Paraku,pa la ku,palaku,paraku,parakw  bnyn,Параку,פאראקו,پاراکو، بنین,パラクー,帕拉庫,파라쿠",
    "subcountry": "Borgou"
  },
  {
    "country": "BJ",
    "geonameid": 2392229,
    "name": "Pahou",
    "alternatenames": "Pahou,Pahu",
    "subcountry": "Atlantique"
  },
  {
    "country": "BJ",
    "geonameid": 2392303,
    "name": "Ouinhi",
    "alternatenames": "",
    "subcountry": "Zou"
  },
  {
    "country": "BJ",
    "geonameid": 2392308,
    "name": "Ouidah",
    "alternatenames": "Fortaleza de Sao Joao Baptista de Ajuda,Fortaleza de São João Baptista de Ajudá,Ouidah,Sao Joao Baptista de Ajuda,São João Baptista de Ajudá,Vidy,Whydah,Wida,sheng yue han bao,Виды,圣约翰堡",
    "subcountry": "Atlantique"
  },
  {
    "country": "BJ",
    "geonameid": 2392505,
    "name": "Nikki",
    "alternatenames": "Nikki,Никки",
    "subcountry": "Borgou"
  },
  {
    "country": "BJ",
    "geonameid": 2392601,
    "name": "Natitingou",
    "alternatenames": "NAE,Natitingou,Natitingu,Натитингу",
    "subcountry": "Atakora"
  },
  {
    "country": "BJ",
    "geonameid": 2392837,
    "name": "Malanville",
    "alternatenames": "Malanvilem,Malanville,Mallanville,Маланвилем",
    "subcountry": "Alibori"
  },
  {
    "country": "BJ",
    "geonameid": 2392897,
    "name": "Lokossa",
    "alternatenames": "Locossa,Lokossa",
    "subcountry": "Mono"
  },
  {
    "country": "BJ",
    "geonameid": 2393551,
    "name": "Ketou",
    "alternatenames": "Ketou,Ketu,Kétou",
    "subcountry": "Plateau"
  },
  {
    "country": "BJ",
    "geonameid": 2393693,
    "name": "Kandi",
    "alternatenames": "KDC,Kandi,Kandis,kandi,kandy  bynn,kang di,kndy  bnyn,Канди,کاندی، بینن,کندی، بنین,カンディ,康迪,칸디",
    "subcountry": "Alibori"
  },
  {
    "country": "BJ",
    "geonameid": 2393883,
    "name": "Hinvi",
    "alternatenames": "Henvi,Hinvi",
    "subcountry": "Atlantique"
  },
  {
    "country": "BJ",
    "geonameid": 2393887,
    "name": "Hevie",
    "alternatenames": "Hevie,Hévié",
    "subcountry": "Atlantique"
  },
  {
    "country": "BJ",
    "geonameid": 2393917,
    "name": "Guilmaro",
    "alternatenames": "Guilmaro",
    "subcountry": "Atakora"
  },
  {
    "country": "BJ",
    "geonameid": 2393947,
    "name": "Grand-Popo",
    "alternatenames": "Ghola,Grand-Popo,Great Popo,Kpla",
    "subcountry": "Mono"
  },
  {
    "country": "BJ",
    "geonameid": 2393994,
    "name": "Goumori",
    "alternatenames": "Goumori",
    "subcountry": "Alibori"
  },
  {
    "country": "BJ",
    "geonameid": 2394545,
    "name": "Dogbo",
    "alternatenames": "",
    "subcountry": "Kouffo"
  },
  {
    "country": "BJ",
    "geonameid": 2394560,
    "name": "Djougou",
    "alternatenames": "DJA,Djougou,Jugu",
    "subcountry": "Donga"
  },
  {
    "country": "BJ",
    "geonameid": 2394711,
    "name": "Dassa-Zoume",
    "alternatenames": "Dassa Zume,Dassa-Zoume,Dassa-Zoumé",
    "subcountry": "Collines"
  },
  {
    "country": "BJ",
    "geonameid": 2394814,
    "name": "Cove",
    "alternatenames": "Kove,Kové",
    "subcountry": "Zou"
  },
  {
    "country": "BJ",
    "geonameid": 2394819,
    "name": "Cotonou",
    "alternatenames": "Appi,COO,Catonou,Cotonou,Cotonu,Cotonú,Katanu,Kotonou,Kotonu,Kotonuo,Kutonu,Kútọnu,ji da nu,ke tuo nu,kotonu,kottonau,kwtwnw,qwtwnw,Κοτονού,Катану,Котону,קוטונו,كوتونو,کوتونو,कोतोनू,ਕੋਤੋਨੂ,கொட்டொனௌ,კოტონუ,コトヌー,吉大奴,科托努,코토누",
    "subcountry": "Littoral"
  },
  {
    "country": "BJ",
    "geonameid": 2394824,
    "name": "Come",
    "alternatenames": "Come,Comé,Kome,Komé",
    "subcountry": "Collines"
  },
  {
    "country": "BJ",
    "geonameid": 2395049,
    "name": "Bohicon",
    "alternatenames": "Bohicon",
    "subcountry": "Zou"
  },
  {
    "country": "BJ",
    "geonameid": 2395127,
    "name": "Beterou",
    "alternatenames": "Beterou,Bétérou",
    "subcountry": "Borgou"
  },
  {
    "country": "BJ",
    "geonameid": 2395182,
    "name": "Bembereke",
    "alternatenames": "Bembereke,Bembèrèkè,Bimbereke,Bimbéréké",
    "subcountry": "Borgou"
  },
  {
    "country": "BJ",
    "geonameid": 2395261,
    "name": "Bassila",
    "alternatenames": "Bassila,basyla  bnyn,Бассіла,باسیلا، بنین",
    "subcountry": "Donga"
  },
  {
    "country": "BJ",
    "geonameid": 2395317,
    "name": "Banikoara",
    "alternatenames": "Banikoara",
    "subcountry": "Alibori"
  },
  {
    "country": "BJ",
    "geonameid": 2395325,
    "name": "Banigbe",
    "alternatenames": "Banibe,Banigbe,Banigbé",
    "subcountry": "Plateau"
  },
  {
    "country": "BJ",
    "geonameid": 2395488,
    "name": "Avakpa",
    "alternatenames": "Avakpa,Avakpa-Motchokpevi",
    "subcountry": "Atlantique"
  },
  {
    "country": "BJ",
    "geonameid": 2395568,
    "name": "Aplahoue",
    "alternatenames": "Aplahoue,Aplahoué,Parahoue,Parahoué,Parahue",
    "subcountry": "Kouffo"
  },
  {
    "country": "BJ",
    "geonameid": 2395591,
    "name": "Angara-Debou",
    "alternatenames": "Angara Deburu,Angara-Debou,Angara-Debu,Angara-Débou,Angara-Débu,https://en.wikipedia.org/wiki/Angarad%C3%A9bou",
    "subcountry": "Alibori"
  },
  {
    "country": "BJ",
    "geonameid": 2395635,
    "name": "Allada",
    "alternatenames": "Allada",
    "subcountry": "Atlantique"
  },
  {
    "country": "BJ",
    "geonameid": 2395859,
    "name": "Adjohon",
    "alternatenames": "Adjohon,Adjohoun,Ajohon",
    "subcountry": "Ouémé"
  },
  {
    "country": "BJ",
    "geonameid": 2395914,
    "name": "Abomey-Calavi",
    "alternatenames": "Abome Calavi,Abomej-Kalavi,Abomey-Calavi,Kalavi,Абомей-Калави",
    "subcountry": "Atlantique"
  },
  {
    "country": "BJ",
    "geonameid": 2395915,
    "name": "Abomey",
    "alternatenames": "Abome,Abomei,Abomej,Abomey,Palacios Reais de Abomei,Palácios Reais de Abomei,Абомей",
    "subcountry": "Zou"
  },
  {
    "country": "BJ",
    "geonameid": 11258052,
    "name": "Houinvigue",
    "alternatenames": "",
    "subcountry": "Ouémé"
  },
  {
    "country": "BJ",
    "geonameid": 11837635,
    "name": "Kpomasse",
    "alternatenames": "",
    "subcountry": "Atlantique"
  }
]
