[
  {
    "country": "SG",
    "geonameid": 1880252,
    "name": "Singapore",
    "alternatenames": "SIN,Sin-ka-po,Singapore,Singapore City,Singapour,Singapur,Singapura,Sinkapoure,Sîn-kâ-po,Tumasik,cinkappur,prathes singkhpor,shingaporu,sigapura,sing-gapol,sing-gapoleu,singapura,singkh por,sngapwr,snghafwrt,syngpwr,xin jia po,xing jia po,Σιγκαπούρη,Сингапур,Сінгапур,סינגפור,سنغافورة,سنگاپور,सिंगापुर,सिंगापूर,ਸਿੰਗਾਪੁਰ,சிங்கப்பூர்,ประเทศสิงคโปร์,สิงค์โปร,ປະເທດສງກະໂປ,ປະເທດສິງກະໂປ,စငကာပနငင,စင်ကာပူနိုင်ငံ,សងហបរ,សិង្ហបុរី,シンガポール,新加坡,星架坡,싱가포르,싱가폴",
    "subcountry": ""
  },
  {
    "country": "SG",
    "geonameid": 1880668,
    "name": "Geylang",
    "alternatenames": "Geylang,Geylang Serai,Geylang Serai Village,geiran,gylang,ya long,گیلانگ,ゲイラン,芽笼",
    "subcountry": ""
  },
  {
    "country": "SG",
    "geonameid": 1882316,
    "name": "Woodlands",
    "alternatenames": "Woodlands,Woodlands New Town",
    "subcountry": ""
  },
  {
    "country": "SG",
    "geonameid": 1882778,
    "name": "Marine Parade",
    "alternatenames": "Malin Bailie,Marine Parade,Marine Parade Estate,Mǎlín Bǎiliè,ma lin bai lie,marin paret,மரின் பரேட்,马林百列",
    "subcountry": ""
  }
]
